storyteller/__init__.py
storyteller/ai.py
storyteller/cli.py
storyteller/db.py
storyteller/export.py
storyteller/lore.py
storyteller/mcp_client.py
storyteller/mcp_server.py
storyteller/plugins.py
storyteller/procedural.py
storyteller/tui.py
ai_storyteller_cli-0.3.0.dist-info/METADATA
ai_storyteller_cli-0.3.0.dist-info/WHEEL
ai_storyteller_cli-0.3.0.dist-info/entry_points.txt
ai_storyteller_cli-0.3.0.dist-info/RECORD
