Metadata-Version: 2.4
Name: ai-storyteller-cli
Version: 0.3.0
Summary: AI Storyteller and DM Assistant
Requires-Python: >=3.10
Requires-Dist: anthropic>=0.3.0
Requires-Dist: google-generativeai>=0.3.0
Requires-Dist: mcp>=0.1.0
Requires-Dist: openai>=1.0.0
Requires-Dist: pydantic>=2.0.0
Requires-Dist: python-dotenv>=1.0.0
Requires-Dist: rich>=13.0.0
Requires-Dist: textual
Requires-Dist: typer>=0.9.0
Provides-Extra: rag
Requires-Dist: lancedb; extra == 'rag'
Requires-Dist: pandas; extra == 'rag'
Requires-Dist: sentence-transformers; extra == 'rag'
